{
  "aamu.edu": {
    "first_seen": "2026-06-23T22:41",
    "last_attempt": "2026-07-02T20:12",
    "retries": 97
  },
  "adhocnews.co.uk": {
    "first_seen": "2026-05-14T08:25",
    "last_attempt": "2026-07-02T20:10",
    "retries": 502
  },
  "adnews.com.au": {
    "first_seen": "2026-06-15T23:19",
    "last_attempt": "2026-07-02T20:10",
    "retries": 166
  },
  "advertiser-tribune.com": {
    "first_seen": "2026-06-09T08:23",
    "last_attempt": "2026-07-02T20:12",
    "retries": 225
  },
  "afp.com": {
    "first_seen": "2026-05-14T08:25",
    "last_attempt": "2026-07-02T20:10",
    "retries": 502
  },
  "agwired.com": {
    "first_seen": "2026-05-27T17:48",
    "last_attempt": "2026-07-02T20:10",
    "retries": 351
  },
  "army.mil": {
    "first_seen": "2026-05-15T22:04",
    "last_attempt": "2026-07-02T20:11",
    "retries": 494
  },
  "armyupress.army.mil": {
    "first_seen": "2026-06-20T18:22",
    "last_attempt": "2026-07-02T20:11",
    "retries": 127
  },
  "au.china-embassy.gov.cn": {
    "first_seen": "2026-07-01T13:24",
    "last_attempt": "2026-07-02T20:12",
    "retries": 15
  },
  "ballstatedailynews.com": {
    "first_seen": "2026-05-27T19:53",
    "last_attempt": "2026-07-02T20:10",
    "retries": 350
  },
  "bandwidthblog.co.za": {
    "first_seen": "2026-06-20T18:21",
    "last_attempt": "2026-07-02T20:10",
    "retries": 127
  },
  "bankingjournal.aba.com": {
    "first_seen": "2026-06-11T00:26",
    "last_attempt": "2026-07-02T20:12",
    "retries": 210
  },
  "beefcentral.com": {
    "first_seen": "2026-05-20T17:26",
    "last_attempt": "2026-07-02T20:12",
    "retries": 426
  },
  "centcom.mil": {
    "first_seen": "2026-07-01T13:22",
    "last_attempt": "2026-07-02T20:10",
    "retries": 15
  },
  "china-embassy.gov.cn": {
    "first_seen": "2026-05-31T14:43",
    "last_attempt": "2026-07-02T20:12",
    "retries": 310
  },
  "chinadailyasia.com": {
    "first_seen": "2026-05-16T06:15",
    "last_attempt": "2026-07-02T20:12",
    "retries": 489
  },
  "cigs.canon": {
    "first_seen": "2026-05-18T10:08",
    "last_attempt": "2026-07-02T20:13",
    "retries": 449
  },
  "coastfm.co.uk": {
    "first_seen": "2026-05-20T22:54",
    "last_attempt": "2026-07-02T20:11",
    "retries": 423
  },
  "cppcc.gov.cn": {
    "first_seen": "2026-05-20T17:27",
    "last_attempt": "2026-07-02T20:12",
    "retries": 426
  },
  "dailycourier.com": {
    "first_seen": "2026-06-22T00:20",
    "last_attempt": "2026-07-02T20:10",
    "retries": 112
  },
  "dailynews.lk": {
    "first_seen": "2026-06-17T23:06",
    "last_attempt": "2026-07-02T20:12",
    "retries": 152
  },
  "dailyvoa.com": {
    "first_seen": "2026-06-27T09:40",
    "last_attempt": "2026-07-02T20:10",
    "retries": 62
  },
  "electronicintifada.net": {
    "first_seen": "2026-05-14T08:25",
    "last_attempt": "2026-07-02T20:10",
    "retries": 502
  },
  "environmentenergyleader.com": {
    "first_seen": "2026-06-04T16:42",
    "last_attempt": "2026-07-02T20:12",
    "retries": 276
  },
  "eucom.mil": {
    "first_seen": "2026-06-04T13:50",
    "last_attempt": "2026-07-02T20:12",
    "retries": 277
  },
  "fcnews.net": {
    "first_seen": "2026-05-21T17:22",
    "last_attempt": "2026-07-02T20:11",
    "retries": 417
  },
  "feeds.texastribune.org": {
    "first_seen": "2026-05-15T22:04",
    "last_attempt": "2026-07-02T20:11",
    "retries": 494
  },
  "fmprc.gov.cn": {
    "first_seen": "2026-05-19T10:07",
    "last_attempt": "2026-07-02T20:12",
    "retries": 438
  },
  "frontporchsports.substack.com": {
    "first_seen": "2026-05-16T11:40",
    "last_attempt": "2026-07-02T20:12",
    "retries": 485
  },
  "groundviews.org": {
    "first_seen": "2026-06-03T10:03",
    "last_attempt": "2026-07-02T20:12",
    "retries": 286
  },
  "id.china-embassy.gov.cn": {
    "first_seen": "2026-06-26T18:28",
    "last_attempt": "2026-07-02T20:10",
    "retries": 69
  },
  "info.gov.hk": {
    "first_seen": "2026-06-23T14:40",
    "last_attempt": "2026-07-02T20:13",
    "retries": 101
  },
  "japanracinginsider.substack.com": {
    "first_seen": "2026-05-31T09:28",
    "last_attempt": "2026-07-02T20:11",
    "retries": 313
  },
  "jbic.go.jp": {
    "first_seen": "2026-06-18T06:29",
    "last_attempt": "2026-07-02T20:12",
    "retries": 150
  },
  "kanerepublican.com": {
    "first_seen": "2026-07-01T02:06",
    "last_attempt": "2026-07-02T20:13",
    "retries": 18
  },
  "kbc.co.ke": {
    "first_seen": "2026-05-20T04:41",
    "last_attempt": "2026-07-02T20:11",
    "retries": 430
  },
  "khmertimeskh.com": {
    "first_seen": "2026-05-25T19:04",
    "last_attempt": "2026-07-02T20:13",
    "retries": 367
  },
  "kwit.org": {
    "first_seen": "2026-06-23T17:07",
    "last_attempt": "2026-07-02T20:12",
    "retries": 100
  },
  "lakeonews.com": {
    "first_seen": "2026-06-13T16:51",
    "last_attempt": "2026-07-02T20:11",
    "retries": 188
  },
  "lankaweb.com": {
    "first_seen": "2026-05-18T01:34",
    "last_attempt": "2026-07-02T20:12",
    "retries": 451
  },
  "lascrucesbulletin.com": {
    "first_seen": "2026-07-01T13:23",
    "last_attempt": "2026-07-02T20:12",
    "retries": 15
  },
  "madisoncourier.com": {
    "first_seen": "2026-05-24T04:41",
    "last_attempt": "2026-07-02T20:13",
    "retries": 386
  },
  "marines.mil": {
    "first_seen": "2026-06-03T21:51",
    "last_attempt": "2026-07-02T20:11",
    "retries": 283
  },
  "marketingreport.one": {
    "first_seen": "2026-05-26T14:25",
    "last_attempt": "2026-07-02T20:10",
    "retries": 360
  },
  "media-cdn.rollcall.com": {
    "first_seen": "2026-06-01T23:46",
    "last_attempt": "2026-07-02T20:10",
    "retries": 296
  },
  "mofa.go.jp": {
    "first_seen": "2026-05-18T16:53",
    "last_attempt": "2026-07-02T20:10",
    "retries": 447
  },
  "mofa.gov.qa": {
    "first_seen": "2026-05-17T15:06",
    "last_attempt": "2026-07-02T20:11",
    "retries": 460
  },
  "mycarrollcountynews.com": {
    "first_seen": "2026-05-17T18:14",
    "last_attempt": "2026-07-02T20:13",
    "retries": 457
  },
  "mycentraloregon.com": {
    "first_seen": "2026-06-13T16:50",
    "last_attempt": "2026-07-02T20:10",
    "retries": 188
  },
  "nationaldefensemagazine.org": {
    "first_seen": "2026-05-14T08:25",
    "last_attempt": "2026-07-02T20:10",
    "retries": 502
  },
  "news.lee.net": {
    "first_seen": "2026-05-26T00:16",
    "last_attempt": "2026-07-02T20:11",
    "retries": 363
  },
  "newsfromwales.co.uk": {
    "first_seen": "2026-07-01T16:03",
    "last_attempt": "2026-07-02T20:12",
    "retries": 14
  },
  "nhk.or.jp": {
    "first_seen": "2026-05-14T08:25",
    "last_attempt": "2026-05-14T08:25",
    "retries": 0
  },
  "northcountrynow.com": {
    "first_seen": "2026-06-07T21:53",
    "last_attempt": "2026-07-02T20:12",
    "retries": 238
  },
  "norwalkreflector.com": {
    "first_seen": "2026-05-30T22:42",
    "last_attempt": "2026-07-02T20:12",
    "retries": 317
  },
  "pacom.mil": {
    "first_seen": "2026-06-02T02:05",
    "last_attempt": "2026-07-02T20:11",
    "retries": 295
  },
  "pipelinepub.com": {
    "first_seen": "2026-06-20T23:57",
    "last_attempt": "2026-07-02T20:12",
    "retries": 123
  },
  "press.fourseasons.com": {
    "first_seen": "2026-06-17T21:31",
    "last_attempt": "2026-07-02T20:12",
    "retries": 153
  },
  "sabanew.net": {
    "first_seen": "2026-05-17T00:58",
    "last_attempt": "2026-07-02T20:12",
    "retries": 472
  },
  "santoandre.biz": {
    "first_seen": "2026-05-26T04:39",
    "last_attempt": "2026-07-02T20:12",
    "retries": 362
  },
  "shorelinemedia.net": {
    "first_seen": "2026-06-15T01:44",
    "last_attempt": "2026-07-02T20:10",
    "retries": 171
  },
  "sinica.edu.tw": {
    "first_seen": "2026-05-15T22:04",
    "last_attempt": "2026-07-02T20:11",
    "retries": 494
  },
  "sjodaily.com": {
    "first_seen": "2026-06-08T00:20",
    "last_attempt": "2026-07-02T20:12",
    "retries": 236
  },
  "spokanepublicradio.org": {
    "first_seen": "2026-06-21T20:21",
    "last_attempt": "2026-07-02T20:10",
    "retries": 115
  },
  "sportingtribune.com": {
    "first_seen": "2026-05-28T12:05",
    "last_attempt": "2026-07-02T20:12",
    "retries": 344
  },
  "static.cfr.org": {
    "first_seen": "2026-05-26T22:49",
    "last_attempt": "2026-07-02T20:12",
    "retries": 356
  },
  "subarutelescope.org": {
    "first_seen": "2026-06-24T05:48",
    "last_attempt": "2026-07-02T20:12",
    "retries": 94
  },
  "surflant.usff.navy.mil": {
    "first_seen": "2026-06-18T17:35",
    "last_attempt": "2026-07-02T20:13",
    "retries": 147
  },
  "tgnews.com.ng": {
    "first_seen": "2026-06-21T15:29",
    "last_attempt": "2026-07-02T20:10",
    "retries": 118
  },
  "thefisherman.com": {
    "first_seen": "2026-05-25T04:57",
    "last_attempt": "2026-07-02T20:11",
    "retries": 371
  },
  "thejewishnews.com": {
    "first_seen": "2026-06-16T17:37",
    "last_attempt": "2026-07-02T20:12",
    "retries": 162
  },
  "thetvratingsguide.com": {
    "first_seen": "2026-06-21T08:54",
    "last_attempt": "2026-07-02T20:12",
    "retries": 121
  },
  "thinkingtaiwan.net": {
    "first_seen": "2026-05-22T12:11",
    "last_attempt": "2026-07-02T20:12",
    "retries": 409
  },
  "tripuratimes.com": {
    "first_seen": "2026-06-07T11:42",
    "last_attempt": "2026-07-02T20:11",
    "retries": 245
  },
  "tvbeurope.com": {
    "first_seen": "2026-05-29T11:55",
    "last_attempt": "2026-07-02T20:12",
    "retries": 336
  },
  "ualrpublicradio.org": {
    "first_seen": "2026-06-03T23:28",
    "last_attempt": "2026-07-02T20:12",
    "retries": 282
  },
  "un.china-mission.gov.cn": {
    "first_seen": "2026-06-18T10:58",
    "last_attempt": "2026-07-02T20:12",
    "retries": 149
  },
  "unitednews.net.ph": {
    "first_seen": "2026-05-21T04:44",
    "last_attempt": "2026-07-02T20:10",
    "retries": 421
  },
  "usafe.af.mil": {
    "first_seen": "2026-06-09T16:44",
    "last_attempt": "2026-07-02T20:11",
    "retries": 222
  },
  "wamnnews.com.au": {
    "first_seen": "2026-05-17T09:57",
    "last_attempt": "2026-07-02T20:13",
    "retries": 464
  },
  "weddings.lavenderhotels.co.uk": {
    "first_seen": "2026-06-29T01:59",
    "last_attempt": "2026-07-02T20:11",
    "retries": 37
  },
  "worldpress.org": {
    "first_seen": "2026-06-21T15:29",
    "last_attempt": "2026-07-02T20:10",
    "retries": 118
  },
  "yourvalley.net": {
    "first_seen": "2026-06-19T16:23",
    "last_attempt": "2026-07-02T20:12",
    "retries": 140
  }
}