{
  "aamu.edu": {
    "first_seen": "2026-06-23T22:41",
    "last_attempt": "2026-07-08T21:23",
    "retries": 173
  },
  "adhocnews.co.uk": {
    "first_seen": "2026-05-14T08:25",
    "last_attempt": "2026-07-08T21:20",
    "retries": 578
  },
  "adnews.com.au": {
    "first_seen": "2026-06-15T23:19",
    "last_attempt": "2026-07-08T21:23",
    "retries": 242
  },
  "advertiser-tribune.com": {
    "first_seen": "2026-06-09T08:23",
    "last_attempt": "2026-07-08T21:22",
    "retries": 301
  },
  "afp.com": {
    "first_seen": "2026-05-14T08:25",
    "last_attempt": "2026-07-08T21:20",
    "retries": 578
  },
  "agwired.com": {
    "first_seen": "2026-05-27T17:48",
    "last_attempt": "2026-07-08T21:23",
    "retries": 427
  },
  "army.mil": {
    "first_seen": "2026-05-15T22:04",
    "last_attempt": "2026-07-08T21:21",
    "retries": 570
  },
  "armyupress.army.mil": {
    "first_seen": "2026-06-20T18:22",
    "last_attempt": "2026-07-08T21:23",
    "retries": 203
  },
  "au.china-embassy.gov.cn": {
    "first_seen": "2026-07-01T13:24",
    "last_attempt": "2026-07-08T21:21",
    "retries": 91
  },
  "ballstatedailynews.com": {
    "first_seen": "2026-05-27T19:53",
    "last_attempt": "2026-07-08T21:22",
    "retries": 426
  },
  "bandwidthblog.co.za": {
    "first_seen": "2026-06-20T18:21",
    "last_attempt": "2026-07-08T21:23",
    "retries": 203
  },
  "bankingjournal.aba.com": {
    "first_seen": "2026-06-11T00:26",
    "last_attempt": "2026-07-08T21:23",
    "retries": 286
  },
  "beefcentral.com": {
    "first_seen": "2026-05-20T17:26",
    "last_attempt": "2026-07-08T21:23",
    "retries": 502
  },
  "bjreview.com": {
    "first_seen": "2026-07-07T11:36",
    "last_attempt": "2026-07-08T21:21",
    "retries": 18
  },
  "centcom.mil": {
    "first_seen": "2026-07-01T13:22",
    "last_attempt": "2026-07-08T21:22",
    "retries": 91
  },
  "china-embassy.gov.cn": {
    "first_seen": "2026-05-31T14:43",
    "last_attempt": "2026-07-08T21:21",
    "retries": 386
  },
  "chinadailyasia.com": {
    "first_seen": "2026-05-16T06:15",
    "last_attempt": "2026-07-08T21:21",
    "retries": 565
  },
  "christianindex.org": {
    "first_seen": "2026-07-08T12:55",
    "last_attempt": "2026-07-08T21:21",
    "retries": 6
  },
  "cigs.canon": {
    "first_seen": "2026-05-18T10:08",
    "last_attempt": "2026-07-08T21:21",
    "retries": 525
  },
  "coastfm.co.uk": {
    "first_seen": "2026-05-20T22:54",
    "last_attempt": "2026-07-08T21:23",
    "retries": 499
  },
  "cppcc.gov.cn": {
    "first_seen": "2026-05-20T17:27",
    "last_attempt": "2026-07-08T21:20",
    "retries": 502
  },
  "dailycourier.com": {
    "first_seen": "2026-06-22T00:20",
    "last_attempt": "2026-07-08T21:21",
    "retries": 188
  },
  "dailynews.lk": {
    "first_seen": "2026-06-17T23:06",
    "last_attempt": "2026-07-08T21:21",
    "retries": 228
  },
  "dailytoreador.com": {
    "first_seen": "2026-07-04T14:21",
    "last_attempt": "2026-07-08T21:22",
    "retries": 53
  },
  "dailyvoa.com": {
    "first_seen": "2026-06-27T09:40",
    "last_attempt": "2026-07-08T21:23",
    "retries": 138
  },
  "dars.gov.et": {
    "first_seen": "2026-07-05T19:58",
    "last_attempt": "2026-07-08T21:23",
    "retries": 34
  },
  "electronicintifada.net": {
    "first_seen": "2026-05-14T08:25",
    "last_attempt": "2026-07-08T21:20",
    "retries": 578
  },
  "environmentenergyleader.com": {
    "first_seen": "2026-06-04T16:42",
    "last_attempt": "2026-07-08T21:23",
    "retries": 352
  },
  "ep.ft.com": {
    "first_seen": "2026-07-05T04:40",
    "last_attempt": "2026-07-08T21:23",
    "retries": 43
  },
  "eucom.mil": {
    "first_seen": "2026-06-04T13:50",
    "last_attempt": "2026-07-08T21:22",
    "retries": 353
  },
  "fcnews.net": {
    "first_seen": "2026-05-21T17:22",
    "last_attempt": "2026-07-08T21:23",
    "retries": 493
  },
  "feeds.texastribune.org": {
    "first_seen": "2026-05-15T22:04",
    "last_attempt": "2026-07-08T21:23",
    "retries": 570
  },
  "fmprc.gov.cn": {
    "first_seen": "2026-05-19T10:07",
    "last_attempt": "2026-07-08T21:21",
    "retries": 514
  },
  "frontporchsports.substack.com": {
    "first_seen": "2026-05-16T11:40",
    "last_attempt": "2026-07-08T21:20",
    "retries": 561
  },
  "gbcghanaonline.com": {
    "first_seen": "2026-07-02T23:48",
    "last_attempt": "2026-07-08T21:22",
    "retries": 74
  },
  "groundviews.org": {
    "first_seen": "2026-06-03T10:03",
    "last_attempt": "2026-07-08T21:23",
    "retries": 362
  },
  "id.china-embassy.gov.cn": {
    "first_seen": "2026-06-26T18:28",
    "last_attempt": "2026-07-08T21:22",
    "retries": 145
  },
  "ifimes.org": {
    "first_seen": "2026-07-07T11:33",
    "last_attempt": "2026-07-08T21:21",
    "retries": 18
  },
  "info.gov.hk": {
    "first_seen": "2026-06-23T14:40",
    "last_attempt": "2026-07-08T21:21",
    "retries": 177
  },
  "japanracinginsider.substack.com": {
    "first_seen": "2026-05-31T09:28",
    "last_attempt": "2026-07-08T21:22",
    "retries": 389
  },
  "jbic.go.jp": {
    "first_seen": "2026-06-18T06:29",
    "last_attempt": "2026-07-08T21:23",
    "retries": 226
  },
  "kanerepublican.com": {
    "first_seen": "2026-07-01T02:06",
    "last_attempt": "2026-07-08T21:21",
    "retries": 94
  },
  "kbc.co.ke": {
    "first_seen": "2026-05-20T04:41",
    "last_attempt": "2026-07-08T21:20",
    "retries": 506
  },
  "kdlg.org": {
    "first_seen": "2026-07-04T07:46",
    "last_attempt": "2026-07-08T21:20",
    "retries": 57
  },
  "khmertimeskh.com": {
    "first_seen": "2026-05-25T19:04",
    "last_attempt": "2026-07-08T21:21",
    "retries": 443
  },
  "kwit.org": {
    "first_seen": "2026-06-23T17:07",
    "last_attempt": "2026-07-08T21:23",
    "retries": 176
  },
  "lakeonews.com": {
    "first_seen": "2026-06-13T16:51",
    "last_attempt": "2026-07-08T21:21",
    "retries": 264
  },
  "lankaweb.com": {
    "first_seen": "2026-05-18T01:34",
    "last_attempt": "2026-07-08T21:23",
    "retries": 527
  },
  "lascrucesbulletin.com": {
    "first_seen": "2026-07-01T13:23",
    "last_attempt": "2026-07-08T21:20",
    "retries": 91
  },
  "madisoncourier.com": {
    "first_seen": "2026-05-24T04:41",
    "last_attempt": "2026-07-08T21:21",
    "retries": 462
  },
  "mahometdaily.com": {
    "first_seen": "2026-07-05T23:32",
    "last_attempt": "2026-07-08T21:21",
    "retries": 31
  },
  "marines.mil": {
    "first_seen": "2026-06-03T21:51",
    "last_attempt": "2026-07-08T21:20",
    "retries": 359
  },
  "marketingreport.one": {
    "first_seen": "2026-05-26T14:25",
    "last_attempt": "2026-07-08T21:21",
    "retries": 436
  },
  "media-cdn.rollcall.com": {
    "first_seen": "2026-06-01T23:46",
    "last_attempt": "2026-07-08T21:20",
    "retries": 372
  },
  "mofa.go.jp": {
    "first_seen": "2026-05-18T16:53",
    "last_attempt": "2026-07-08T21:21",
    "retries": 523
  },
  "mofa.gov.qa": {
    "first_seen": "2026-05-17T15:06",
    "last_attempt": "2026-07-08T21:23",
    "retries": 536
  },
  "mycarrollcountynews.com": {
    "first_seen": "2026-05-17T18:14",
    "last_attempt": "2026-07-08T21:22",
    "retries": 533
  },
  "mycentraloregon.com": {
    "first_seen": "2026-06-13T16:50",
    "last_attempt": "2026-07-08T21:21",
    "retries": 264
  },
  "nationaldefensemagazine.org": {
    "first_seen": "2026-05-14T08:25",
    "last_attempt": "2026-07-08T21:20",
    "retries": 578
  },
  "news.lee.net": {
    "first_seen": "2026-05-26T00:16",
    "last_attempt": "2026-07-08T21:22",
    "retries": 439
  },
  "newsfromwales.co.uk": {
    "first_seen": "2026-07-01T16:03",
    "last_attempt": "2026-07-08T21:21",
    "retries": 90
  },
  "nhk.or.jp": {
    "first_seen": "2026-05-14T08:25",
    "last_attempt": "2026-05-14T08:25",
    "retries": 0
  },
  "northcountrynow.com": {
    "first_seen": "2026-06-07T21:53",
    "last_attempt": "2026-07-08T21:22",
    "retries": 314
  },
  "norwalkreflector.com": {
    "first_seen": "2026-05-30T22:42",
    "last_attempt": "2026-07-08T21:23",
    "retries": 393
  },
  "pacom.mil": {
    "first_seen": "2026-06-02T02:05",
    "last_attempt": "2026-07-08T21:23",
    "retries": 371
  },
  "pipelinepub.com": {
    "first_seen": "2026-06-20T23:57",
    "last_attempt": "2026-07-08T21:20",
    "retries": 199
  },
  "press.fourseasons.com": {
    "first_seen": "2026-06-17T21:31",
    "last_attempt": "2026-07-08T21:22",
    "retries": 229
  },
  "sabanew.net": {
    "first_seen": "2026-05-17T00:58",
    "last_attempt": "2026-07-08T21:21",
    "retries": 548
  },
  "santoandre.biz": {
    "first_seen": "2026-05-26T04:39",
    "last_attempt": "2026-07-08T21:23",
    "retries": 438
  },
  "shorelinemedia.net": {
    "first_seen": "2026-06-15T01:44",
    "last_attempt": "2026-07-08T21:22",
    "retries": 247
  },
  "sinica.edu.tw": {
    "first_seen": "2026-05-15T22:04",
    "last_attempt": "2026-07-08T21:23",
    "retries": 570
  },
  "sjodaily.com": {
    "first_seen": "2026-06-08T00:20",
    "last_attempt": "2026-07-08T21:21",
    "retries": 312
  },
  "spokanepublicradio.org": {
    "first_seen": "2026-06-21T20:21",
    "last_attempt": "2026-07-08T21:23",
    "retries": 191
  },
  "sportingtribune.com": {
    "first_seen": "2026-05-28T12:05",
    "last_attempt": "2026-07-08T21:23",
    "retries": 420
  },
  "static.cfr.org": {
    "first_seen": "2026-05-26T22:49",
    "last_attempt": "2026-07-08T21:21",
    "retries": 432
  },
  "subarutelescope.org": {
    "first_seen": "2026-06-24T05:48",
    "last_attempt": "2026-07-08T21:21",
    "retries": 170
  },
  "surflant.usff.navy.mil": {
    "first_seen": "2026-06-18T17:35",
    "last_attempt": "2026-07-08T21:21",
    "retries": 223
  },
  "tgnews.com.ng": {
    "first_seen": "2026-06-21T15:29",
    "last_attempt": "2026-07-08T21:22",
    "retries": 194
  },
  "thefisherman.com": {
    "first_seen": "2026-05-25T04:57",
    "last_attempt": "2026-07-08T21:20",
    "retries": 447
  },
  "thejewishnews.com": {
    "first_seen": "2026-06-16T17:37",
    "last_attempt": "2026-07-08T21:23",
    "retries": 238
  },
  "thetvratingsguide.com": {
    "first_seen": "2026-06-21T08:54",
    "last_attempt": "2026-07-08T21:21",
    "retries": 197
  },
  "thinkingtaiwan.net": {
    "first_seen": "2026-05-22T12:11",
    "last_attempt": "2026-07-08T21:21",
    "retries": 485
  },
  "tripuratimes.com": {
    "first_seen": "2026-06-07T11:42",
    "last_attempt": "2026-07-08T21:21",
    "retries": 321
  },
  "tvbeurope.com": {
    "first_seen": "2026-05-29T11:55",
    "last_attempt": "2026-07-08T21:23",
    "retries": 412
  },
  "ualrpublicradio.org": {
    "first_seen": "2026-06-03T23:28",
    "last_attempt": "2026-07-08T21:21",
    "retries": 358
  },
  "un.china-mission.gov.cn": {
    "first_seen": "2026-06-18T10:58",
    "last_attempt": "2026-07-08T21:23",
    "retries": 225
  },
  "unitednews.net.ph": {
    "first_seen": "2026-05-21T04:44",
    "last_attempt": "2026-07-08T21:23",
    "retries": 497
  },
  "usafe.af.mil": {
    "first_seen": "2026-06-09T16:44",
    "last_attempt": "2026-07-08T21:20",
    "retries": 298
  },
  "wamnnews.com.au": {
    "first_seen": "2026-05-17T09:57",
    "last_attempt": "2026-07-08T21:22",
    "retries": 540
  },
  "weddings.lavenderhotels.co.uk": {
    "first_seen": "2026-06-29T01:59",
    "last_attempt": "2026-07-08T21:20",
    "retries": 113
  },
  "wmuk.org": {
    "first_seen": "2026-07-04T23:16",
    "last_attempt": "2026-07-08T21:21",
    "retries": 45
  },
  "worldpress.org": {
    "first_seen": "2026-06-21T15:29",
    "last_attempt": "2026-07-08T21:23",
    "retries": 194
  },
  "yourvalley.net": {
    "first_seen": "2026-06-19T16:23",
    "last_attempt": "2026-07-08T21:22",
    "retries": 216
  }
}